create_fastapi_project/.DS_Store
create_fastapi_project/__main__.py
create_fastapi_project/create_app.py
create_fastapi_project/helpers/__init__.py
create_fastapi_project/helpers/git.py
create_fastapi_project/helpers/install.py
create_fastapi_project/main.py
create_fastapi_project/templates/__init__.py
create_fastapi_project/templates/basic/.env.example
create_fastapi_project/templates/basic/.gitignore
create_fastapi_project/templates/basic/Makefile
create_fastapi_project/templates/basic/README.md
create_fastapi_project/templates/basic/backend/Dockerfile
create_fastapi_project/templates/basic/backend/app/README.md
create_fastapi_project/templates/basic/backend/app/app/__init__.py
create_fastapi_project/templates/basic/backend/app/app/api/__init__.py
create_fastapi_project/templates/basic/backend/app/app/api/v1/__init__.py
create_fastapi_project/templates/basic/backend/app/app/api/v1/api.py
create_fastapi_project/templates/basic/backend/app/app/api/v1/endpoints/__init__.py
create_fastapi_project/templates/basic/backend/app/app/api/v1/endpoints/weather.py
create_fastapi_project/templates/basic/backend/app/app/core/__init__.py
create_fastapi_project/templates/basic/backend/app/app/core/config.py
create_fastapi_project/templates/basic/backend/app/app/main.py
create_fastapi_project/templates/basic/backend/app/app/schemas/response_schema.py
create_fastapi_project/templates/basic/backend/app/app/utils/__init__.py
create_fastapi_project/templates/basic/backend/app/app/utils/exceptions/__init__.py
create_fastapi_project/templates/basic/backend/app/app/utils/exceptions/common_exception.py
create_fastapi_project/templates/basic/backend/app/app/utils/exceptions/user_exceptions.py
create_fastapi_project/templates/basic/backend/app/app/utils/exceptions/user_follow_exceptions.py
create_fastapi_project/templates/basic/backend/app/app/utils/partial.py
create_fastapi_project/templates/basic/backend/app/app/utils/uuid6.py
create_fastapi_project-0.2.5.dist-info/LICENSE
create_fastapi_project-0.2.5.dist-info/METADATA
create_fastapi_project-0.2.5.dist-info/WHEEL
create_fastapi_project-0.2.5.dist-info/entry_points.txt
create_fastapi_project-0.2.5.dist-info/RECORD
