Metadata-Version: 2.1
Name: create-fastapi-project
Version: 0.2.5
Summary: 
Author: jonra1993
Author-email: jvargas@allient.io
Requires-Python: >=3.10,<4.0
Classifier: Programming Language :: Python :: 3
Classifier: Programming Language :: Python :: 3.10
Classifier: Programming Language :: Python :: 3.11
Classifier: Programming Language :: Python :: 3.12
Requires-Dist: python-dotenv (>=1.0.0,<2.0.0)
Requires-Dist: questionary (>=2.0.0,<3.0.0)
Requires-Dist: toml (>=0.10.2,<0.11.0)
Requires-Dist: typer[all] (>=0.12.0,<0.13.0)
